{
    "name": "Get out of the   huge maze",
    "description": "",
    "dependencies": {
        "device": "*"
    },
    "files": [
        "main.blocks",
        "main.ts",
        "README.md",
        "assets.json",
        "tilemap.g.jres",
        "tilemap.g.ts"
    ],
    "testFiles": [
        "test.ts"
    ],
    "targetVersions": {
        "branch": "v1.8.30",
        "tag": "v1.8.30",
        "commits": "https://github.com/microsoft/pxt-arcade/commits/825ea9e52c6d33c12777ef204c0406661995353f",
        "target": "1.8.30",
        "pxt": "7.4.31",
        "targetId": "arcade"
    },
    "supportedTargets": [
        "arcade"
    ],
    "preferredEditor": "blocksprj"
}
